dir_diary/__init__.py
dir_diary/classifier.py
dir_diary/cli.py
dir_diary/client.py
dir_diary/datastructures.py
dir_diary/file_handler.py
dir_diary/mapper.py
dir_diary/openai_chatbot.py
dir_diary/summarize.py
dir_diary/summarizer.py
dir_diary/validators.py
dir_diary-0.3.3.dist-info/entry_points.txt
dir_diary-0.3.3.dist-info/LICENSE
dir_diary-0.3.3.dist-info/METADATA
dir_diary-0.3.3.dist-info/WHEEL
dir_diary-0.3.3.dist-info/RECORD
