Metadata-Version: 2.1
Name: dir-diary
Version: 0.3.3
Summary: A Python CLI tool to summarize your software project folder with LLMs
License: MIT
Author: Christopher Carroll Smith
Author-email: christopher.smith@promptlytechnologies.com
Requires-Python: >=3.9,<4.0
Classifier: License :: OSI Approved :: MIT License
Classifier: Programming Language :: Python :: 3
Classifier: Programming Language :: Python :: 3.9
Classifier: Programming Language :: Python :: 3.10
Classifier: Programming Language :: Python :: 3.11
Requires-Dist: click (>=8.1.7,<9.0.0)
Requires-Dist: llm_cost_estimation (>=0.1.4,<0.2.0)
Requires-Dist: openai (>=0.28.0,<0.29.0)
Requires-Dist: pathspec (>=0.11.2,<0.12.0)
Requires-Dist: pydantic (>=2.3.0,<3.0.0)
Requires-Dist: python-dotenv (>=1.0.0,<2.0.0)
